{
  "current_info": {
    "icon": "https://img.buzzsight.co/apk/icon/com.higame.par.prison.survival.prank.call.video.chat.png",
    "title": "Prison Phone: Fake Call&Chat",
    "ratings": "4.7",
    "downloads": "113M",
    "age": "4+"
  },
  "appinfo_list": [
    {
      "name": "Name",
      "value": "Prison Phone: Fake Call&Chat"
    },
    {
      "name": "category",
      "value": "Casual"
    },
    {
      "name": "Price",
      "value": "0"
    },
    {
      "name": "Safety",
      "value": "100% Safe"
    },
    {
      "name": "Developer",
      "value": "HIGAME Studio"
    },
    {
      "name": "Version",
      "value": "7.0"
    }
  ],
  "app_screen": [
    "https://play-lh.googleusercontent.com/muoXarzKVL5TS0iuUGlCYtm8TpYyb9cWbwUfP53IwrIwM0aweurvOmQYmt9g-82yqs8",
    "https://play-lh.googleusercontent.com/cn9vpF2TgrC2ykIHax90EEZaAw-XR_XG6SNKPY6hmfxOv9QRnB62vQ58NMjg9oBEOw",
    "https://play-lh.googleusercontent.com/5PUPDKxAD8lISOtTiknBWxp8pWZDP68v0mrIEmHTpFVhRJ3goRy7Atk4WZztQPr3d3ry",
    "https://play-lh.googleusercontent.com/Zykt2lQZHY2GrJDjd_AbT5Esc0UThdcr6w1tcw0Nkan3s4jD4F7fQSjHoKs8JInzu1s2",
    "https://play-lh.googleusercontent.com/WrpgjY42D70VJ88leA1RNmn5BRSWmx-BCa5WEmRIVXPk9KW53tl8VsWIWJ6F0n9deAM",
    "https://play-lh.googleusercontent.com/DmYTszJ3AUsrbOTo_LA39tp9LPnvSUs5WUgSUzAcqODMclU5q1LjDu8xBzAZpcH64WyU",
    "https://play-lh.googleusercontent.com/StEVNPEqD9T_7-FTjD5np9_TPimtM5OvIIReZPUCqtgeZTt2_YdLHe5yikN8a2r18Zw",
    "https://play-lh.googleusercontent.com/hEdSm8KDcB9EKThDt5fMNOItShIbtOAov2YxBM9nmV-lCZfW80JoIr8OSrhdCBWxeGP9",
    "https://play-lh.googleusercontent.com/ZrpX1d4mle52feYFUfM0THfNx807Sj_j15UXvNAVb8j_RbPDPtFsIFCHgU7cuUPkiHY",
    "https://play-lh.googleusercontent.com/RiyF4Patjh6uYrCjwr7Ipj_8mkrRDz9UAdifJVF18OKK5bxf2xzwppL1S4B1c15GqLc",
    "https://play-lh.googleusercontent.com/HPfvTrepiTNiuFQoIFyoK2EiUUgV4YBJ6ZB2rc6r8J2LS2EalZ8wO5In_8oRc8dqeQ",
    "https://play-lh.googleusercontent.com/IGlD-2vBsv0y2LPomfpjx9bNyLzDcWW7tF20a3pWjUfAOEhziFP2yuYQSP4kYAvdoQ",
    "https://play-lh.googleusercontent.com/0gD6YwrmgllqkIuvdemExCySZ1golMqhJHNE4fEEdMljIv-lbdog-mB6m0znHx90b-4",
    "https://play-lh.googleusercontent.com/0wrIJKxcVwRCRkJOHZSRj3gvLuEFA5FoE2GZNbx5AwzeW-NcB4GXjGYNTpTKXtYI2Q",
    "https://play-lh.googleusercontent.com/pGbiXqHko1_0jPuqU9bdxrEiGXz5bIwimXUAkc5NovHKybUlUlAN_oObDj17_X3Lq6Q",
    "https://play-lh.googleusercontent.com/-yKVCXYCvCwvEJV3TAQDSXaeBTl7Fc5fHEQfDy9JnSM2uv3XkEDc9j7JmKx6D_f3Zw",
    "https://play-lh.googleusercontent.com/tj7dEpu5EdNu7W2vxCBLiY33tfmeMacBBW1LmP7hp0jGhJZ8XvWDVTFm2s-nt5F0OKA",
    "https://play-lh.googleusercontent.com/bHGIlVn_KXWIowS1FPn361RH_BVkzP9c_Mzu6jh4oMhgb4q4NINJe-iO1P0MJ7phew"
  ],
  "app_descript": "<h1>Prison Phone: Fake Call&amp;Chat</h1>\n<h2>Brief</h2>\n<p>Are you a fan of thrilling survival games and intense prison stories? If so, <strong>Prison Phone: Fake Call&amp;Chat</strong> is the ultimate prank app for you! This entertaining app allows you to make realistic fake video calls and engage in chats with iconic prison characters from your favorite movies and shows. Get ready to immerse yourself in a world of pranks!</p>\n<h2>Core Features</h2>\n<ul>\n<li>🎥 <strong>Realistic Fake Calls</strong>: Experience engaging fake calls that feel genuine, enhancing your prank game.</li>\n<li>🎭 <strong>Famous Characters</strong>: Choose from a variety of popular prison and survival characters to prank your friends.</li>\n<li>📞 <strong>High-Quality Video Calls</strong>: Enjoy crystal-clear video that mimics real conversations, making the prank more convincing.</li>\n<li>📲 <strong>User-Friendly Interface</strong>: The app is designed for easy navigation, ensuring a smooth experience for all users.</li>\n<li>🔥 <strong>Completely Free</strong>: Enjoy all features without any hidden costs, making it accessible to everyone!</li>\n</ul>\n<h2>Pros</h2>\n<ul>\n<li>👍 <strong>Engaging Experience</strong>: Interact as if the call is real, providing a fun and immersive prank experience.</li>\n<li>🎉 <strong>Perfect for Pranking</strong>: Ideal for surprising friends with unexpected and hilarious calls.</li>\n<li>🆓 <strong>No Cost</strong>: The app is free to use, allowing users access without any financial commitment.</li>\n<li>🔄 <strong>Easy to Use</strong>: Quick and simple setup makes it user-friendly for all age groups.</li>\n</ul>\n<h2>Cons</h2>\n<ul>\n<li>👎 <strong>Limited Characters</strong>: The selection of characters may not cater to everyone's preferences.</li>\n<li>⏳ <strong>Possible Ads</strong>: Users could encounter advertisements, which might disrupt the experience.</li>\n<li>🛠️ <strong>No Customization Options</strong>: Users may wish for more personalization features for calls and chats.</li>\n<li>❌ <strong>Not for Serious Use</strong>: Its primary function is for pranks, so it's not suited for serious communications.</li>\n</ul>\n<h2>Price</h2>\n<p>💵 <strong>Pricing</strong>: The app is completely free with no in-app purchases required.</p>",
  "related_apps": [
    {
      "link": "https://hot.apkzonic.com/en/details/com-mirai-funnyjoke-pranksounds-spranky/54464.html",
      "icon": "https://img.buzzsight.co/apk/icon/com.mirai.funnyjoke.pranksounds.spranky.png",
      "name": "Funny Prank: Monster Sound",
      "categoryLink": "/en/categories/casual/39",
      "category": "Casual",
      "rating": "3.4"
    },
    {
      "link": "https://hot.apkzonic.com/en/details/com-beateacher-game-qwepi-glc/54452.html",
      "icon": "https://img.buzzsight.co/apk/icon/com.beateacher.game.qwepi.glc.png",
      "name": "Be A Teacher Mini App",
      "categoryLink": "/en/categories/casual/39",
      "category": "Casual",
      "rating": "4.5"
    },
    {
      "link": "https://hot.apkzonic.com/en/details/com-pixeland-talkingbuddy/54440.html",
      "icon": "https://img.buzzsight.co/apk/icon/com.pixeland.talkingbuddy.png",
      "name": "My Talking Slimy - Slime Buddy",
      "categoryLink": "/en/categories/casual/39",
      "category": "Casual",
      "rating": "4.3"
    },
    {
      "link": "https://hot.apkzonic.com/en/details/com-hmbl-perfect-clean-tidy-asmr/54428.html",
      "icon": "https://img.buzzsight.co/apk/icon/com.hmbl.perfect.clean.tidy.asmr.png",
      "name": "Perfect Clean: Tidy ASMR",
      "categoryLink": "/en/categories/casual/39",
      "category": "Casual",
      "rating": "4.4"
    },
    {
      "link": "https://hot.apkzonic.com/en/details/com-cat-hole-puzzle-aos/54368.html",
      "icon": "https://img.buzzsight.co/apk/icon/com.cat.hole.puzzle.aos.png",
      "name": "Drop the Cat!",
      "categoryLink": "/en/categories/casual/39",
      "category": "Casual",
      "rating": "4.4"
    },
    {
      "link": "https://hot.apkzonic.com/en/details/com-jigsolitare-anti-stress-game/54345.html",
      "icon": "https://img.buzzsight.co/apk/icon/com.jigsolitare.anti.stress.game.png",
      "name": "Jigsolitaire: Anti Stress",
      "categoryLink": "/en/categories/casual/39",
      "category": "Casual",
      "rating": "4.5"
    },
    {
      "link": "https://hot.apkzonic.com/en/details/com-battle-deskmate/54075.html",
      "icon": "https://img.buzzsight.co/apk/icon/com.battle.deskmate.png",
      "name": "Puzzle Collection: Mini Games",
      "categoryLink": "/en/categories/casual/39",
      "category": "Casual",
      "rating": "4.5"
    },
    {
      "link": "https://hot.apkzonic.com/en/details/no-wifi-offline-games-puzzle-games/54063.html",
      "icon": "https://img.buzzsight.co/apk/icon/no.wifi.offline.games.puzzle.games.png",
      "name": "Mini Games Offline All in One",
      "categoryLink": "/en/categories/casual/39",
      "category": "Casual",
      "rating": "4.5"
    }
  ]
}