{
  "current_info": {
    "icon": "https://img.buzzsight.co/apk/icon/com.pandaexpress.app.png",
    "title": "Panda Express",
    "ratings": "4.7",
    "downloads": "100M",
    "age": "4+"
  },
  "appinfo_list": [
    {
      "name": "Name",
      "value": "Panda Express"
    },
    {
      "name": "category",
      "value": "Food & Drink"
    },
    {
      "name": "Price",
      "value": "Free"
    },
    {
      "name": "Safety",
      "value": "100% Safe"
    },
    {
      "name": "Developer",
      "value": "Panda Restaurant Group, Inc."
    },
    {
      "name": "Version",
      "value": "5.0.0"
    }
  ],
  "app_screen": [
    "https://play-lh.googleusercontent.com/qOro6T-7xxdRb17jTe-n7RjNocfa97P4u8W5I3eWGRRUo30ljOIDbRSBtker60jyd-4",
    "https://play-lh.googleusercontent.com/_krMi4bSfAxYhFer5nTpZ9UGVTPTpnyhxZ6TeVVg5nMMbu83tivw-4VaCExKUPX2UZQ",
    "https://play-lh.googleusercontent.com/bLHgIFq0uumkjF1sJCwk8A7PDBBwx_nb5FOvqipm3AN69nXv5qeSuVFr-KA80Cjaiw",
    "https://play-lh.googleusercontent.com/gxl8vcbv6NkjPtFgasg3xN2PUT_tqn1eyks4GgKnReXnkIHRl9g7Y1BAGboiDFhrj4E",
    "https://play-lh.googleusercontent.com/BNO4H45Wx7wyryGITunqHIbHY8TkvQmr3vV6JYXId8iACERfePYY6SEfXr5Hn0hdDyc",
    "https://play-lh.googleusercontent.com/VDiuhvgBV6e2hulGPfyHB2Dos3-2MjdRju1HUtAnk_DPlgAwfgRv1RgnLN_mrwuT-3k0",
    "https://play-lh.googleusercontent.com/w-HQ4wD-oKHIOZ0xK4B0rdPMcOyARXlBVrgOgCSf6bQ93E-gR6X-SWruC2K0RmT7LQ",
    "https://play-lh.googleusercontent.com/mpMzXhamucUic9r2Dxz1uGHRX9zGEXX5cmsHROlwHcrtF2_S295bUxaijKuRIbb2qw",
    "https://play-lh.googleusercontent.com/8hSYaD9rTT0qrRiw3BW9yUQA8GIfV--rApk8RqQQ4seKtitOSLBFfYgHSlVYllWXUQ",
    "https://play-lh.googleusercontent.com/GsHTKwUbUX-fUwcB0RoXUPhd3FGrMXQT2g6h_B5oRyqI-m8BRSAosR5dG2YV2wOo9Ng",
    "https://play-lh.googleusercontent.com/TP0nJc9Urget1j6vH_r6aGZk8RCs4GP5QbMQ0xfIz2oNVVxNR1ly_138YkSooB4N0Qru",
    "https://play-lh.googleusercontent.com/Dt5ZMypMHLrjDCEFjZz3JvQANuK-fipO2yMTVPNeGHbhhtJcQ4LDO5W0dev0St_3TGU"
  ],
  "app_descript": "<h3>Panda Express App</h3>\n<p>Get ready to experience the convenience of delicious Asian cuisine right at your fingertips with the Panda Express app. Catering to your cravings, this mobile application seamlessly integrates dining and ordering services to ensure you can enjoy Panda Express anytime and anywhere.</p>\n<h4>Core Features 📌</h4>\n<ul>\n<li><strong>Flexible Ordering:</strong> Choose dine-in, take-out, or delivery to suit your schedule. Order for immediate satisfaction or plan ahead by scheduling for a later time. 🍽️</li>\n<li><strong>Favorites Reordering:</strong> Easily save your preferred meals and reorder them with just a single tap. Your tasty go-to dishes are now just a tap away. 💾</li>\n<li><strong>Catering Made Simple:</strong> Effortlessly plan your next event with Panda Express's catering service. Select your desired sides and entrees, and leave the rest to them. 🎉</li>\n</ul>\n<h4>Pros 👍</h4>\n<ul>\n<li><strong>Convenience at Your Service:</strong> No more waiting in lines. Whether for an individual meal or a group gathering, get your food exactly how and when you want it.</li>\n<li><strong>Customized Experience:</strong> Save multiple favorite meals and access them quickly for a personalized ordering experience.</li>\n<li><strong>Hassle-Free Catering:</strong> Planning events becomes a breeze with reliable catering options that promise to delight your guests.</li>\n<li><strong>User-Friendly Interface:</strong> The app's intuitive design makes navigation, ordering, and customizing meals straightforward.</li>\n</ul>\n<h4>Cons 👎</h4>\n<ul>\n<li><strong>Limited to Panda Express:</strong> As a brand-specific app, your Asian cuisine choices are confined to the Panda Express menu.</li>\n<li><strong>Delivery Area Restrictions:</strong> Delivery services may not cover all geographical areas, which could limit access for some users.</li>\n<li><strong>Connectivity Dependency:</strong> An active internet connection is essential for accessing the app's features, which might be troublesome in low coverage areas.</li>\n<li><strong>Potential for Additional Fees:</strong> Depending on the order, delivery, and location, there might be extra charges beyond the food costs.</li>\n</ul>\n<h4>Price 💵</h4>\n<p>The Panda Express app is free to download and use. However, standard food costs and potential delivery fees apply. There may also be additional charges for catering services.</p>\n<h4>Community 🕸️</h4>\n<p>The Panda Express community is thriving and can be further explored through various social media and online platforms.</p>\n<ul>\n<li>Official Site: <a href=\"https://www.pandaexpress.com/\" rel=\"noopener noreferrer\" target=\"_blank\">Panda Express</a></li>\n<li>YouTube Channel: <a href=\"https://www.youtube.com/user/PandaExpressTV/\" rel=\"noopener noreferrer\" target=\"_blank\">Panda Express</a></li>\n</ul>\n<p>Join fellow food lovers by engaging with Panda Express across these platforms to stay updated on the latest deals, menu additions, and more!</p>",
  "related_apps": [
    {
      "link": "/details/com-buzzfeed-tasty/16927.html",
      "icon": "https://img.buzzsight.co/apk/icon/com.buzzfeed.tasty.png",
      "name": "Tasty",
      "categoryLink": "/en/categories/food.drink/29",
      "category": "Food & Drink",
      "rating": "4.7"
    },
    {
      "link": "/details/com-hacklatino-chingon-android/15837.html",
      "icon": "https://img.buzzsight.co/apk/icon/com.hacklatino.chingon.android.png",
      "name": "Hack Latino",
      "categoryLink": "/en/categories/food.drink/29",
      "category": "Food & Drink",
      "rating": "4.2"
    },
    {
      "link": "/details/com-postmates-android/4464.html",
      "icon": "https://img.buzzsight.co/apk/icon/com.postmates.android.png",
      "name": "Postmates - Food Delivery",
      "categoryLink": "/en/categories/food.drink/29",
      "category": "Food & Drink",
      "rating": "4.3"
    },
    {
      "link": "/details/com-seamlessweb-android-view/4463.html",
      "icon": "https://img.buzzsight.co/apk/icon/com.seamlessweb.android.view.png",
      "name": "Seamless: Local Food Delivery",
      "categoryLink": "/en/categories/food.drink/29",
      "category": "Food & Drink",
      "rating": "4.6"
    },
    {
      "link": "/details/com-trycaviar-customer/4462.html",
      "icon": "https://img.buzzsight.co/apk/icon/com.trycaviar.customer.png",
      "name": "Caviar - Order Food Delivery",
      "categoryLink": "/en/categories/food.drink/29",
      "category": "Food & Drink",
      "rating": "4.6"
    },
    {
      "link": "/details/com-chownow-discover/4461.html",
      "icon": "https://img.buzzsight.co/apk/icon/com.chownow.discover.png",
      "name": "ChowNow: Local Food Ordering",
      "categoryLink": "/en/categories/food.drink/29",
      "category": "Food & Drink",
      "rating": "4.6"
    },
    {
      "link": "/details/com-toasttab-consumer/4460.html",
      "icon": "https://img.buzzsight.co/apk/icon/com.toasttab.consumer.png",
      "name": "Toast Takeout & Delivery",
      "categoryLink": "/en/categories/food.drink/29",
      "category": "Food & Drink",
      "rating": "4.7"
    },
    {
      "link": "/details/menulog-au/3667.html",
      "icon": "https://img.buzzsight.co/apk/icon/com.menulog.m.png",
      "name": "Menulog AU",
      "categoryLink": "/en/categories/food.drink/29",
      "category": "Food & Drink",
      "rating": "4.2"
    }
  ]
}