{
  "title": "Ourtime - Meet 50 Singles: Who’s the Ultimate Matchmaker?",
  "review_html": "<div class=\"reviewcon reviewcon-n topicpageaticle\">\n<p>Looking for love, companionship, or just someone to share a laugh with? Ourtime is here to make it happen! Designed exclusively for singles over 50, this app is your gateway to meeting like-minded individuals in your area. Whether you’re seeking romance, friendship, or a meaningful connection, Ourtime simplifies the process with its fun and engaging platform.</p>\n<p>What makes Ourtime stand out? It’s tailored specifically for the 50+ crowd, offering a simple and user-friendly interface that even the least tech-savvy individuals can navigate with ease. From the moment you sign up, you’ll appreciate the clean, intuitive design that makes the whole experience approachable and stress-free.</p>\n<p>The matching process is straightforward: set up your profile, discover potential matches, and connect through likes, messages, or even flirts. Real-life success stories from users like Linda, 56, and John, 61, showcase how effective Ourtime is in fostering genuine connections. To make the most of your experience, remember to be honest in your profile, upload quality photos, and stay active on the app.</p>\n<p>Ourtime also offers unique features to enhance your journey. The Flirt Button lets you break the ice with ease, while Local Events help you meet people in person. Plus, Match Preferences ensure you’re paired with individuals who share your interests. And let’s not forget the quirky profiles and memorable first-date stories that add a touch of humor and personality to the experience.</p>\n<div class=\"adv_slot_container\"></div>\n<p>Got questions? The app’s FAQs cover everything from cost and safety to usability for non-tech-savvy users. In essence, Ourtime is more than just a dating app—it’s a vibrant community where singles over 50 can connect, share, and find love. Ready to meet your match? Download Ourtime today and start your journey!</p>\n<p><a href=\"https://dl.xlap.top/details/com-peoplemedia-ourtime/15463.html\">ourtime - meet 50 singles and start your journey today!</a></p> </div>",
  "section_title": "Editor's Choice",
  "editor_box_items": [
    {
      "coverlink": "/article/transform-your-photos-with-face-dance-ai-photo-animator/618.html",
      "img_src": "assets/img/Uploads/articles/20250402/c9eeb27434f35486331c396a65e63373.png",
      "edt_small_tag": "Transform Your Photos with Face Dance: AI Photo Animator"
    },
    {
      "coverlink": "/article/ai-powered-interior-design-create-your-dream-home-in-5-steps-with-home-ai/347.html",
      "img_src": "assets/img/Uploads/articles/20250228/05902886dd11417dd49b6ef43edd46a6.png",
      "edt_small_tag": "AI-Powered Interior Design: Create Your Dream Home in 5 Steps with Home AI"
    },
    {
      "coverlink": "/article/dive-into-my-supermarket-simulator-3d-your-retail-adventure-awaits/8882.html",
      "img_src": "assets/img/Uploads/articles/20250820/692b026046c15e177e4026a5047cbda5.png",
      "edt_small_tag": "🛒 Dive into My Supermarket Simulator 3D: Your Retail Adventure Awaits!"
    }
  ]
}